Workbook

Sheet 📊 Dashboard & Synthèse
A1: 🇲🇦 PROGRAMME DE MIGRATION SHOPIFY VERS SITE PROPRIÉTAIRE - MAROC
A3: Pipeline de prospection stratégique & Étude d'impact financier pour les marques e-commerce marocaines
A5: TOTAL PROSPECTS QUALIFIÉS | D5: PROSPECTS 'TRÈS HAUTE' PRIORITÉ | F5: ÉCONOMIES MOY. ANNUELLES / CLIENT | H5: FUITE DE DEVISES TOTALE / AN
A6: =COUNTA('🎯 Base Prospects (35)'!A4:A38) | D6: =COUNTIF('🎯 Base Prospects (35)'!M4:M38, "*Très Haute*") | F6: =AVERAGE('🎯 Base Prospects (35)'!L4:L38)*12 | H6: =SUM('🎯 Base Prospects (35)'!L4:L38)*12
A7: Boutiques Shopify au Maroc | D7: Marques prêtes pour migration | F7: Dirhams (MAD) économisés/an | H7: MAD gaspillés en abonnements US
A9: RÉPARTITION PAR CATÉGORIE / NICHE | I9: PRIORITÉ DE PROSPECTION
A10: Catégorie Principale | B10: Nombre de Boutiques | C10: % du Total | D10: Enjeux Clés de Migration | I10: Niveau de Priorité | K10: Nombre
A11: Bijouterie, Joaillerie & Horlogerie | B11: 8 | C11: 0.22857143 | D11: Paniers élevés, besoin d'élégance et de confiance maximale | I11: 🔥 Très Haute (Hot Leads) | K11: =COUNTIF('🎯 Base Prospects (35)'!M4:M38, "*Très Haute*")
A12: Mode, Prêt-à-porter, Caftans & Abayas | B12: 8 | C12: 0.22857143 | D12: Gros volumes, trafic intense pendant les drops, mobile 90%+ | I12: ⚡ Haute Priorité | K12: =COUNTIF('🎯 Base Prospects (35)'!M4:M38, "*Haute*") - COUNTIF('🎯 Base Prospects (35)'!M4:M38, "*Très Haute*")
A13: Maroquinerie & Chaussures en cuir | B13: 5 | C13: 0.14285714 | D13: Artisanat d'excellence (Fès/Marrakech), fort taux de conversion | I13: 📌 Moyenne Priorité | K13: =COUNTIF('🎯 Base Prospects (35)'!M4:M38, "*Moyenne*")
A14: Parfumerie, Cosmétique & Bien-être | B14: 6 | C14: 0.17142857 | D14: Produits récurrents, COD massif, besoin de bundles natifs
A15: Maison, Décoration d'intérieur & Art | B15: 5 | C15: 0.14285714 | D15: Configurateurs visuels, livraison par ville, commandes B2B/B2C
A16: High-Tech, Domotique & Santé | B16: 3 | C16: 0.085714286 | D16: Fiches techniques riches, SAV et facturation ICE obligatoire
A18: LES 4 DOULEURS MAJEURES DE SHOPIFY POUR LES COMMERÇANTS MAROCAINS
A20: 1. Pression sur la Dotation E-commerce | D20: Les commerçants paient l'abonnement Shopify ($39-$399) + 5 à 10 apps ($100-$300) par mois en USD sur leur carte bancaire internationale. Cela épuise leur quota officiel (dotation e-commerce) au détriment de leurs dépenses publicitaires Facebook/TikTok Ads indispensables.
A21: 2. Pénalité de 2% sur les Commandes COD | D21: Shopify n'ayant pas de passerelle 'Shopify Payments' au Maroc, la plateforme prélève des frais de transaction additionnels (0.5% à 2%) sur toutes les commandes, y compris le Cash on Delivery (paiement à la livraison) !
A22: 3. Checkout Inadapté au Marché Marocain | D22: Le checkout par défaut de Shopify compte 3 étapes et exige code postal, province, etc. Les Marocains n'ont pas de code postal. Les apps de formulaire COD (Releasit/EasySell) coûtent un abonnement mensuel et ralentissent la boutique.
A23: 4. Lenteur Mobile & Dépendance Totale | D23: Chaque app Shopify injecte des scripts tiers externes qui font chuter le score Google PageSpeed mobile sous les 40/100 sur le réseau 4G marocain, diminuant drastiquement le retour sur investissement des publicités.

Sheet 🎯 Base Prospects (35)
A1: BASE DE PROSPECTION STRATÉGIQUE - 35 BOUTIQUES SHOPIFY AU MAROC À MIGRER
A3: N° | B3: Marque (Smiya) | C3: Niche / Catégorie | D3: Site Web (URL) | E3: Ville / Siège | F3: WhatsApp Business | G3: Lien Direct WhatsApp | H3: Email Contact | I3: Instagram | J3: Positionnement | K3: Coût Shopify Estimé ($/m) | L3: Coût Shopify Estimé (DH/m) | M3: Priorité | N3: Douleur Principale Shopify | O3: Stack Recommandée | P3: Accroche Personnalisée / Pitch | Q3: Statut Prospection | R3: Dernier Contact | S3: Prochaine Action
A4: 1 | B4: Anulus Joaillerie | C4: Bijouterie & Horlogerie (Or & Argent) | D4: https://anulus.ma | E4: Casablanca | F4: +212 6 39 15 68 83 | G4: 💬 Ouvrir WhatsApp | H4: contact@anulus.ma | I4: Instagram | J4: Haut de Gamme / Luxe | K4: 180 | L4: =K4*10 | M4: 🔥 Très Haute | N4: Plafond dotation e-commerce consommé en devises USD + frais de 2% sur chaque transaction + lenteur sur mobile due aux apps de zoom/avis. | O4: Next.js + Tailwind + CMI / COD | P4: Éliminez les 18 000 DH/an de frais Shopify récurrents et offrez une expérience d'achat joaillerie ultra-rapide et sécurisée 100% marocaine. | Q4: ✅ Démo & Audit Prêts | R4: Audit & Démo Next.js générés | S4: Envoyer note vocale WhatsApp & email
A5: 2 | B5: Ma Montre Maroc | C5: Horlogerie & Montres Homme/Femme | D5: https://mamontre.ma | E5: Casablanca | F5: +212 6 45 22 20 09 | G5: 💬 Ouvrir WhatsApp | H5: mamontre.ma@gmail.com | I5: Instagram | J5: Mid-range / Volume | K5: 150 | L5: =K5*10 | M5: Haute | N5: Dépendance à Releasit/EasySell pour le Cash-On-Delivery. Coût mensuel Shopify + pénalité de 2% sur chaque commande COD. | O5: WooCommerce Headless ou Next.js | P5: Checkout COD en 1 clic sans abonnement mensuel d'app tierce + confirmation automatique des commandes par WhatsApp API. | Q5: ✅ Démo & Audit Prêts | R5: Audit & Démo Next.js générés | S5: Envoyer note vocale WhatsApp & email
A6: 3 | B6: Dynasty Maroc | C6: Linge de maison & Décoration | D6: https://dynasty.ma | E6: Casablanca | F6: +212 7 63 77 80 49 | G6: 💬 Ouvrir WhatsApp | H6: contact@dynasty.ma | I6: Instagram | J6: Haut de Gamme | K6: 220 | L6: =K6*10 | M6: Haute | N6: Catalogue produits riche nécessitant des applications de personnalisation lourdes qui ralentissent le chargement sur mobile 4G. | O6: Next.js + Shopify Headless ou Custom | P6: Un site vitrine e-commerce ultra-fluide avec temps de chargement < 1 sec, design sur-mesure digne des plus grands éditeurs de textile. | Q6: À Contacter | R6: - | S6: Premier contact WhatsApp / Audio personnalisé
A7: 4 | B7: Flex Shoes | C7: Chaussures cuir véritable & Maroquinerie | D7: https://flexshoes.ma | E7: Fès / Casablanca | F7: +212 6 70 59 88 44 | G7: 💬 Ouvrir WhatsApp | H7: flexshoes.ma@gmail.com | I7: Instagram | J7: Mid-range / Artisanat Cuir | K7: 140 | L7: =K7*10 | M7: 🔥 Très Haute | N7: Taux d'abandon élevé sur mobile causé par le tunnel Shopify multi-étapes non adapté aux habitudes d'achat COD marocaines. | O7: Next.js + Tailwind / Fast COD | P7: Formulaire direct Nom + Téléphone + Ville + Pointure avec notification livreur intégrée (AMEEX / Cathedis) et zéro abonnement en devises. | Q7: À Contacter | R7: - | S7: Premier contact WhatsApp / Audio personnalisé
A8: 5 | B8: Sacoluxe | C8: Sacs à main & Maroquinerie de luxe | D8: https://sacoluxe.com | E8: Casablanca | F8: +212 6 45 22 20 09 | G8: 💬 Ouvrir WhatsApp | H8: sacoluxe@gmail.com | I8: Instagram | J8: Luxe / Tendance | K8: 160 | L8: =K8*10 | M8: Moyenne | N8: Identité visuelle limitée par les thèmes Shopify standards et commissions inutiles sur ventes. | O8: Next.js + Tailwind CSS | P8: Créez une véritable expérience boutique de luxe personnalisée sans payer de royalties mensuelles à Shopify. | Q8: À Contacter | R8: - | S8: Premier contact WhatsApp / Audio personnalisé
A9: 6 | B9: Maison de Mode | C9: Mode, Chaussures, Sacs & Bijoux | D9: https://maisondemode.ma | E9: Casablanca | F9: +212 7 00 91 87 91 | G9: 💬 Ouvrir WhatsApp | H9: contact@maisondemode.ma | I9: Instagram | J9: Mid-range | K9: 200 | L9: =K9*10 | M9: Haute | N9: Nombreux plugins installés (PageFly, Judge.me, COD form) créant un goulet d'étranglement de vitesse et un coût cumulé de ~200$/mois. | O9: Next.js + Direct COD + Supabase/SQL | P9: Économisez plus de 24 000 DH par an d'abonnements d'apps et améliorez votre taux de conversion mobile de +25%. | Q9: À Contacter | R9: - | S9: Premier contact WhatsApp / Audio personnalisé
A10: 7 | B10: Aurea Accessories | C10: Bijoux & Accessoires acier inoxydable | D10: https://aureaaccessories.ma | E10: Rabat | F10: +212 6 84 90 25 11 | G10: 💬 Ouvrir WhatsApp | H10: contact@aureaaccessories.ma | I10: Instagram | J10: Access / Trendy | K10: 130 | L10: =K10*10 | M10: 🔥 Très Haute | N10: Panier moyen bas (150-250 DH), les frais Shopify et applications grèvent lourdement la marge nette. | O10: Nuxt / Next.js ou WooCommerce Pro | P10: Pour les paniers à 199 DH, chaque dirham de frais Shopify compte. Libérez vos marges et investissez vos devises dans TikTok Ads. | Q10: À Contacter | R10: - | S10: Premier contact WhatsApp / Audio personnalisé
A11: 8 | B11: Viba Bijoux | C11: Bijoux & Parures pour femmes | D11: https://vibabijoux.ma | E11: Casablanca | F11: +212 6 45 22 20 09 | G11: 💬 Ouvrir WhatsApp | H11: vibabijoux@gmail.com | I11: Instagram | J11: Mid-range | K11: 140 | L11: =K11*10 | M11: Moyenne | N11: Partage potentiel d'infrastructure/coordonnées avec d'autres marques (même numéro que Sacoluxe/MaMontre). Besoin de singularisation. | O11: Next.js e-commerce | P11: Distinguez votre marque avec une plateforme propriétaire unique, découplée des templates Shopify génériques. | Q11: À Contacter | R11: - | S11: Premier contact WhatsApp / Audio personnalisé
A12: 9 | B12: Bleather Maroc | C12: Maroquinerie & Cuir artisanal | D12: https://bleather.ma | E12: Marrakech | F12: +212 6 03 69 51 77 | G12: 💬 Ouvrir WhatsApp | H12: contact.bleather@gmail.com | I12: Instagram | J12: Haut de Gamme / Export | K12: 250 | L12: =K12*10 | M12: 🔥 Très Haute | N12: Frais de transaction élevés sur les ventes internationales et limitations de passerelles de paiement locales en dirhams. | O12: Next.js + CMI + Stripe Multi-currency | P12: Un site bilingue/multidevise (MAD + EUR/USD) avec CMI intégré pour le Maroc et Stripe pour l'international sans commission 2% Shopify. | Q12: À Contacter | R12: - | S12: Premier contact WhatsApp / Audio personnalisé
A13: 10 | B13: Feskin Cuir | C13: Maroquinerie artisanale & Cuir de Fès | D13: https://feskin.ma | E13: Fès | F13: +212 6 61 78 90 12 | G13: 💬 Ouvrir WhatsApp | H13: contact@feskin.ma | I13: Instagram | J13: Artisanal / Authentique | K13: 120 | L13: =K13*10 | M13: Haute | N13: Paiement de factures en dollars épuisant la dotation e-commerce de l'artisan sans justification technique. | O13: WooCommerce Optimisé ou Custom Node/React | P13: Payez votre hébergement en dirhams au Maroc, conservez 100% de votre dotation e-commerce pour vos publicités. | Q13: À Contacter | R13: - | S13: Premier contact WhatsApp / Audio personnalisé
A14: 11 | B14: Clakovs Brustel | C14: Chaussures de ville & Prêt-à-porter | D14: https://clakovsbrustel.ma | E14: Casablanca | F14: +212 6 66 32 91 19 | G14: 💬 Ouvrir WhatsApp | H14: contact@clakovsbrustel.com | I14: Instagram | J14: Haut de Gamme Élégant | K14: 190 | L14: =K14*10 | M14: Haute | N14: Expérience d'achat standardisée ne reflétant pas le prestige de la marque et les exigences d'une clientèle masculine haut de gamme. | O14: Next.js + Tailwind + CMI/COD | P14: Sublimez votre image de marque avec une interface épurée, ultra-rapide et sans les bannières ou restrictions de Shopify. | Q14: À Contacter | R14: - | S14: Premier contact WhatsApp / Audio personnalisé
A15: 12 | B15: Makushop | C15: Parfumerie & Soins de beauté | D15: https://makushop.ma | E15: Casablanca | F15: +212 6 97 83 88 05 | G15: 💬 Ouvrir WhatsApp | H15: contact@makushop.ma | I15: Instagram | J15: Mass Market / Beauté | K15: 150 | L15: =K15*10 | M15: Haute | N15: Fort volume de commandes COD entraînant des frais transactionnels excessifs et des conflits de scripts d'upsell. | O15: Next.js E-commerce Custom | P15: Module d'upsell 'Achetez 2, obtenez le 3ème à -50%' natif et sans frais mensuels récurrents. | Q15: À Contacter | R15: - | S15: Premier contact WhatsApp / Audio personnalisé
... A38: 35 | B38: Chabi Chic | C38: Art de vivre, céramique artisanale & Déco | D38: https://chabi-chic.com | E38: Marrakech | F38: +212 6 10 10 47 54 | G38: 💬 Ouvrir WhatsApp | H38: contact@chabi-chic.com | I38: Instagram | J38: Luxe Artisanal / International | K38: 450 | L38: =K38*10 | M38: 🔥 Très Haute | N38: Énorme coût Shopify Plus / Advanced + commissions sur les ventes internationales pesant des dizaines de milliers de DH. | O38: Next.js / Headless Commerce Multi-entrepôts | P38: Plateforme headless sur-mesure d'envergure mondiale, économisant plus de 50 000 DH/an de commissions de plateforme avec design haute couture. | Q38: À Contacter | R38: - | S38: Premier contact WhatsApp / Audio personnalisé
A39: TOTAL DES FRAIS MENSUELS ESTIMÉS SHOPIFY (ÉCONOMIES POTENTIELLES POUR CES MARQUES) : | K39: =SUM(K4:K38) | L39: =SUM(L4:L38)

Sheet 💡 Scripts & Argumentaire
A1: SCRIPTS DE PROSPECTION COMMERCIALE & GUIDE D'OBJECTIONS (MAROC)
A3: 1. Premier Message WhatsApp d'Accroche (En Darija Pro)
A4: Objectif : Obtenir une réponse du gérant / fondateur en 2 minutes en touchant directement au portefeuille (Devises / Frais cachés)
A5: Salam Si [Prénom du Gérant] / L'équipe de [Nom de la Marque], tbarkellah 3likom service w les produits dyalkom top ! Kanchouf bli le site dyalkom khddam b Shopify. Comme vous le savez, m3a les limitations dyal la dotation e-commerce w l'Office des Changes f l-Meghrib, Shopify kayakhod likom : 1. Abonnement mensuel en dollars ($39 à $299) li kayconsomi likom l-plafond dyal carte e-commerce li khtajito l les pubs (Facebook/TikTok). 2. Des frais cachés dyal 2% 3la kol commande COD (paiement à la livraison) hit makaynch Shopify Payments f l-Maghreb. 3. Des applications mensuelles (PageFly, COD forms, Judge.me) li kayt9alo le site 3la l-mobile w kaytiyho le taux de conversion. 7na kan-développiw des sites e-commerce sur-mesure (Next.js / 100% dialek) : ✅ Zéro abonnement mensuel en devises (site dyalek pour toujours). ✅ Formulaire COD 1-clic ultra-rapide (< 1 seconde de chargement). ✅ Confirmation WhatsApp automatique w liaison m3a les sociétés de livraison (Cathedis, Ozon, AMEEX...). Wach 3ndkom 10 d9ayeq had la semaine ndiro un audit gratuit dyal le site dyalkom w n-wariwkom ch7al t9do t-wfro par an ?
A7: 2. Script de Premier Contact par Email (En Français Professionnel)
A8: Objet : [Nom de la Marque] - Économisez 25 000 DH/an sur vos frais Shopify & Boostez votre conversion mobile
A9: Bonjour [Nom du Dirigeant / Équipe E-commerce], Félicitations pour le développement de la marque [Nom de la Marque], votre positionnement sur le marché marocain est remarquable. En analysant votre boutique en ligne [URL], nous avons constaté que vous utilisez la plateforme Shopify. Si Shopify est une solution pratique au démarrage, elle devient un véritable frein pour les marques marocaines en phase d'accélération : 1. Pression sur votre Dotation E-commerce : Entre le forfait Shopify et les applications tierces indispensables (PageFly, formulaires COD, avis), vous dépensez entre 1 500 et 3 000 DH/mois en devises internationales, réduisant d'autant votre budget publicitaire Meta et TikTok. 2. Commissions de 2% sur le Cash-on-Delivery : Faute de Shopify Payments au Maroc, vous payez une pénalité sur chaque commande livrée. 3. Vitesse Mobile limitée : L'accumulation d'apps ralentit le chargement sur smartphone (4G Maroc), ce qui entraîne une perte de 20% à 30% des visiteurs payés via la pub. Notre offre : Nous migrons votre boutique vers votre propre infrastructure e-commerce propriétaire haute performance (Next.js / Technologie moderne) : • 0 DH d'abonnement en devises (vous êtes 100% propriétaire de votre boutique). • Formulaire Cash on Delivery optimisé en 2 clics avec validation par WhatsApp. • Vitesse instantanée (Score Google PageSpeed 95+/100) pour maximiser le ROI de vos pubs. Seriez-vous disponible pour un échange rapide de 15 minutes cette semaine (Visio ou WhatsApp) afin d'examiner l'audit technique et financier de votre boutique ? Bien cordialement, [Votre Nom / Votre Agence] [Votre Téléphone WhatsApp]
A11: 3. Traitement des Principales Objections des Clients Marocains
A12: Comment répondre aux doutes les plus fréquents pour conclure le contrat
A13: OBJECTION 1 : 'Shopify c'est simple, comment je vais gérer mes produits sans Shopify ?' RÉPONSE : 'Vous aurez un tableau de bord (Back-office) en français ou arabe encore plus simple que Shopify ! Vous pourrez ajouter des produits, modifier les prix, voir les commandes et imprimer les bordereaux de livraison en 1 clic depuis votre PC ou votre téléphone, sans aucune ligne de code.' OBJECTION 2 : 'La migration va-t-elle couper mes ventes ou me faire perdre mes données ?' RÉPONSE : 'Zéro interruption de service ! Nous importons l'intégralité de vos clients, historiques de commandes et fiches produits sur votre nouveau site. Le basculement se fait en 10 minutes durant la nuit. Vos campagnes publicitaires continuent de tourner sans perturbation.' OBJECTION 3 : 'Combien coûte la création du site par rapport à Shopify ?' RÉPONSE : 'Sur Shopify, vous payez entre 18 000 et 35 000 DH chaque année, indéfiniment. Avec un site propriétaire, vous faites un investissement unique amorti en 6 à 9 mois grâce aux économies d'abonnements et au gain de conversion, puis votre site vous appartient à vie.' OBJECTION 4 : 'Et la sécurité / hébergement ?' RÉPONSE : 'Votre site est hébergé sur des serveurs Cloud mondiaux sécurisés (Vercel / Cloudflare) avec certificat SSL bancaire et sauvegardes quotidiennes automatiques. C'est le même niveau de sécurité que les géants mondiaux.'

Sheet 💰 Calculateur ROI Migration
A1: SIMULATEUR DE RENTABILITÉ : SHOPIFY VS SITE PROPRIÉTAIRE (NEXT.JS)
A3: PARAMÈTRES DE LA BOUTIQUE DU CLIENT (MODIFIABLES)
A4: Paramètre | B4: Valeur | C4: Description / Hypothèse
A5: Chiffre d'Affaires Mensuel Estimé (DH) | B5: 150000 | C5: CA moyen d'un e-commerçant marocain actif
A6: Nombre de commandes par mois | B6: 500 | C6: Panier moyen ~300 DH
A7: Plan Shopify utilisé ($/mois) | B7: 39 | C7: Basic: $39 / Shopify: $105 / Advanced: $399
A8: Frais d'applications Shopify mensuels ($/mois) | B8: 80 | C8: EasySell/Releasit, PageFly, Judge.me, etc.
A9: Commission Shopify sur transactions non-Shopify Payments | B9: 0.02 | C9: 2.0% pour Basic, 1.0% pour Shopify
A10: Taux de change USD -> MAD | B10: 10 | C10: 1 USD = 10 MAD environ
A11: Coût de développement du Site Propriétaire (Devis Agence DH) | B11: 18000 | C11: Investissement initial one-shot
A12: Coût d'hébergement serveur mensuel du Site Propriétaire (DH) | B12: 100 | C12: Vercel / Hetzner / Hostinger
A14: COMPARAISON DES COÛTS RÉELS SUR 1 AN ET 3 ANS
A15: Poste de Coût | B15: Formule / Calcul | C15: Shopify (1 An) | D15: Site Propre (1 An) | E15: Shopify (3 Ans) | F15: Site Propre (3 Ans)
A16: Frais d'Abonnement Plateforme | B16: (Plan $ * Taux * Mois) | C16: =B7*B10*12 | D16: 0 | E16: =B7*B10*36 | F16: 0
A17: Frais des Applications Tierces | B17: (Apps $ * Taux * Mois) | C17: =B8*B10*12 | D17: 0 | E17: =B8*B10*36 | F17: 0
A18: Commissions Transactions (2% sur CA) | B18: (CA Mensuel * % Comm * Mois) | C18: =B5*B9*12 | D18: 0 | E18: =B5*B9*36 | F18: 0
A19: Frais de Développement Initial | B19: Création sur-mesure | C19: 0 | D19: =B11 | E19: 0 | F19: =B11
A20: Frais d'Hébergement & Maintenance | B20: Serveur Cloud | C20: 0 | D20: =B12*12 | E20: 0 | F20: =B12*36
A21: COÛT TOTAL CUMULÉ | B21: Total des dépenses | C21: =SUM(C16:C20) | D21: =SUM(D16:D20) | E21: =SUM(E16:E20) | F21: =SUM(F16:F20)
A23: ÉCONOMIE NETTE RÉALISÉE DÈS LA PREMIÈRE ANNÉE : | D23: =C21-D21
A26: ÉCONOMIE NETTE TOTALE SUR 3 ANS : | D26: =E21-F21

Sheet 📋 Suivi Prospection CRM
A1: PIPELINE COMMERCIAL & JOURNAL DE SUIVI DES RELANCES
A3: Date Prise Contact | B3: Marque | C3: Interlocuteur | D3: Canal Utilisé | E3: Réponse Obtenue | F3: Statut Actuel | G3: Objection Majeure | H3: Valeur Devis Potentiel (DH) | I3: Date Prochaine Relance | J3: Action Prévue | K3: Commentaires
A4: 26/10/2026 | B4: Anulus Joaillerie | C4: Fondateur / E-commerce Mgr | D4: WhatsApp Direct | E4: Démo & Audit validés | F4: 2. Prêt pour Envoi | G4: - | H4: 18000 | I4: Immédiat | J4: Envoyer note vocale WhatsApp & pitch email | K4: Priorité 🔥 Très Haute - Démo Next.js prête dans leads/Anulus_Joaillerie/
A5: 26/10/2026 | B5: Ma Montre Maroc | C5: Fondateur / E-commerce Mgr | D5: WhatsApp Direct | E5: Démo & Audit validés | F5: 2. Prêt pour Envoi | G5: - | H5: 18000 | I5: Immédiat | J5: Envoyer note vocale WhatsApp & pitch email | K5: Priorité Haute - Démo Next.js prête dans leads/Ma_Montre_Maroc/
A6: À planifier | B6: Dynasty Maroc | C6: Fondateur / E-commerce Mgr | D6: WhatsApp Direct | E6: En attente premier message | F6: 1. Nouveau Lead | G6: - | H6: 18000 | I6: J+2 | J6: Envoyer note vocale WhatsApp personnalisée | K6: Priorité Haute - Numéro : +212 7 63 77 80 49
A7: À planifier | B7: Flex Shoes | C7: Fondateur / E-commerce Mgr | D7: WhatsApp Direct | E7: En attente premier message | F7: 1. Nouveau Lead | G7: - | H7: 18000 | I7: J+2 | J7: Envoyer note vocale WhatsApp personnalisée | K7: Priorité 🔥 Très Haute - Numéro : +212 6 70 59 88 44
A8: À planifier | B8: Maison de Mode | C8: Fondateur / E-commerce Mgr | D8: WhatsApp Direct | E8: En attente premier message | F8: 1. Nouveau Lead | G8: - | H8: 18000 | I8: J+2 | J8: Envoyer note vocale WhatsApp personnalisée | K8: Priorité Haute - Numéro : +212 7 00 91 87 91
A9: À planifier | B9: Aurea Accessories | C9: Fondateur / E-commerce Mgr | D9: WhatsApp Direct | E9: En attente premier message | F9: 1. Nouveau Lead | G9: - | H9: 18000 | I9: J+2 | J9: Envoyer note vocale WhatsApp personnalisée | K9: Priorité 🔥 Très Haute - Numéro : +212 6 84 90 25 11
A10: À planifier | B10: Bleather Maroc | C10: Fondateur / E-commerce Mgr | D10: WhatsApp Direct | E10: En attente premier message | F10: 1. Nouveau Lead | G10: - | H10: 18000 | I10: J+2 | J10: Envoyer note vocale WhatsApp personnalisée | K10: Priorité 🔥 Très Haute - Numéro : +212 6 03 69 51 77
A11: À planifier | B11: Feskin Cuir | C11: Fondateur / E-commerce Mgr | D11: WhatsApp Direct | E11: En attente premier message | F11: 1. Nouveau Lead | G11: - | H11: 18000 | I11: J+2 | J11: Envoyer note vocale WhatsApp personnalisée | K11: Priorité Haute - Numéro : +212 6 61 78 90 12
A12: À planifier | B12: Clakovs Brustel | C12: Fondateur / E-commerce Mgr | D12: WhatsApp Direct | E12: En attente premier message | F12: 1. Nouveau Lead | G12: - | H12: 18000 | I12: J+2 | J12: Envoyer note vocale WhatsApp personnalisée | K12: Priorité Haute - Numéro : +212 6 66 32 91 19
A13: À planifier | B13: Makushop | C13: Fondateur / E-commerce Mgr | D13: WhatsApp Direct | E13: En attente premier message | F13: 1. Nouveau Lead | G13: - | H13: 18000 | I13: J+2 | J13: Envoyer note vocale WhatsApp personnalisée | K13: Priorité Haute - Numéro : +212 6 97 83 88 05
A14: À planifier | B14: 70mai Maroc | C14: Fondateur / E-commerce Mgr | D14: WhatsApp Direct | E14: En attente premier message | F14: 1. Nouveau Lead | G14: - | H14: 18000 | I14: J+2 | J14: Envoyer note vocale WhatsApp personnalisée | K14: Priorité 🔥 Très Haute - Numéro : +212 6 71 45 03 67
A15: À planifier | B15: Minisouq Maroc | C15: Fondateur / E-commerce Mgr | D15: WhatsApp Direct | E15: En attente premier message | F15: 1. Nouveau Lead | G15: - | H15: 18000 | I15: J+2 | J15: Envoyer note vocale WhatsApp personnalisée | K15: Priorité Haute - Numéro : +212 6 55 44 33 22
... A34: À planifier | B34: Chabi Chic | C34: Fondateur / E-commerce Mgr | D34: WhatsApp Direct | E34: En attente premier message | F34: 1. Nouveau Lead | G34: - | H34: 18000 | I34: J+2 | J34: Envoyer note vocale WhatsApp personnalisée | K34: Priorité 🔥 Très Haute - Numéro : +212 6 10 10 47 54
